assistant
test
